mbf_pandas_msgpack-0.7.1.dist-info/LICENSE.md
mbf_pandas_msgpack-0.7.1.dist-info/RECORD
mbf_pandas_msgpack-0.7.1.dist-info/WHEEL
mbf_pandas_msgpack-0.7.1.dist-info/top_level.txt
mbf_pandas_msgpack-0.7.1.dist-info/METADATA
mbf_pandas_msgpack/__init__.py
mbf_pandas_msgpack/_move.cpython-37m-darwin.so
mbf_pandas_msgpack/packers.py
mbf_pandas_msgpack/msgpack/_packer.cpython-37m-darwin.so
mbf_pandas_msgpack/msgpack/_version.py
mbf_pandas_msgpack/msgpack/__init__.py
mbf_pandas_msgpack/msgpack/exceptions.py
mbf_pandas_msgpack/msgpack/_unpacker.cpython-37m-darwin.so
